csemodule/__init__.py
csemodule-0.1.0.dist-info/METADATA
csemodule-0.1.0.dist-info/WHEEL
csemodule-0.1.0.dist-info/top_level.txt
csemodule-0.1.0.dist-info/RECORD
